anyencrypt/__init__.py
anyencrypt/__main__.py
anyencrypt/cli.py
anyencrypt/crypto.py
anyencrypt/i18n.py
anyencrypt/locales/messages.pot
anyencrypt/locales/en/LC_MESSAGES/messages.mo
anyencrypt/locales/en/LC_MESSAGES/messages.po
anyencrypt/locales/es/LC_MESSAGES/messages.mo
anyencrypt/locales/es/LC_MESSAGES/messages.po
anyencrypt/locales/fr/LC_MESSAGES/messages.mo
anyencrypt/locales/fr/LC_MESSAGES/messages.po
anyencrypt/locales/ja/LC_MESSAGES/messages.mo
anyencrypt/locales/ja/LC_MESSAGES/messages.po
anyencrypt/locales/zh_CN/LC_MESSAGES/messages.mo
anyencrypt/locales/zh_CN/LC_MESSAGES/messages.po
anyencrypt-0.5.0.dist-info/licenses/LICENSE
anyencrypt-0.5.0.dist-info/METADATA
anyencrypt-0.5.0.dist-info/WHEEL
anyencrypt-0.5.0.dist-info/entry_points.txt
anyencrypt-0.5.0.dist-info/top_level.txt
anyencrypt-0.5.0.dist-info/RECORD
